{
  "ALY": [
    "ALLEY",
    "ALLEE",
    "ALLY",
    "ALY"
  ],
  "ANX": [
    "ANEX",
    "ANX",
    "ANNEX",
    "ANNX"
  ],
  "ARC": [
    "ARCADE",
    "ARC"
  ],
  "AVE": [
    "AVENUE",
    "AV",
    "AVE",
    "AVEN",
    "AVENU",
    "AVENUE",
    "AVN",
    "AVNUE"
  ],
  "BYU": [
    "BAYOU",
    "BAYOO"
  ],
  "BCH": [
    "BEACH",
    "BCH"
  ],
  "BND": [
    "BEND",
    "BND"
  ],
  "BLF": [
    "BLUFF",
    "BLF",
    "BLUF"
  ],
  "BLFS": [
    "BLUFFS",
    "BLFS"
  ],
  "BTM": [
    "BOTTOM",
    "BOT",
    "BTM",
    "BOTTM"
  ],
  "BLVD": [
    "BOULEVARD",
    "BLVD",
    "BOUL",
    "BOULV"
  ],
  "BR": [
    "BRANCH",
    "BR",
    "BRNCH"
  ],
  "BRG": [
    "BRIDGE",
    "BRDGE",
    "BRG"
  ],
  "BRK": [
    "BROOK",
    "BRK"
  ],
  "BRKS": [
    "BROOKS",
    "BRKS"
  ],
  "BG": [
    "BURG",
    "BG"
  ],
  "BGS": [
    "BURGS",
    "BGS"
  ],
  "BYP": [
    "BYPASS",
    "BYP",
    "BYPA",
    "BYPAS",
    "BYPS"
  ],
  "CP": [
    "CAMP",
    "CP",
    "CMP"
  ],
  "CYN": [
    "CANYON",
    "CANYN",
    "CYN",
    "CNYN"
  ],
  "CPE": [
    "CAPE",
    "CPE"
  ],
  "CSWY": [
    "CAUSEWAY",
    "CSWY",
    "CAUSWA"
  ],
  "CTR": [
    "CENTER",
    "CEN",
    "CTR",
    "CENT",
    "CENTR",
    "CENTRE",
    "CNTER",
    "CNTR"
  ],
  "CTRS": [
    "CENTERS",
    "CTRS"
  ],
  "CIR": [
    "CIRCLE",
    "CIR",
    "CIRC",
    "CIRCL",
    "CRCL",
    "CRCLE"
  ],
  "CIRS": [
    "CIRCLES",
    "CIRS"
  ],
  "CLF": [
    "CLIFF",
    "CLF"
  ],
  "CLFS": [
    "CLIFFS",
    "CLFS"
  ],
  "CLB": [
    "CLUB",
    "CLB"
  ],
  "CMN": [
    "COMMON",
    "CMN"
  ],
  "CMNS": [
    "COMMONS",
    "CMNS"
  ],
  "COR": [
    "CORNER",
    "COR"
  ],
  "CORS": [
    "CORNERS",
    "CORS"
  ],
  "CRSE": [
    "COURSE",
    "CRSE"
  ],
  "CT": [
    "COURT",
    "CT"
  ],
  "CTS": [
    "COURTS",
    "CTS"
  ],
  "CV": [
    "COVE",
    "CV"
  ],
  "CVS": [
    "COVES",
    "CVS"
  ],
  "CRK": [
    "CREEK",
    "CRK"
  ],
  "CRES": [
    "CRESCENT",
    "CRES",
    "CRSENT",
    "CRSNT"
  ],
  "CRST": [
    "CREST",
    "CRST"
  ],
  "XING": [
    "CROSSING",
    "XING",
    "CRSSNG"
  ],
  "XRD": [
    "CROSSROAD",
    "XRD"
  ],
  "XRDS": [
    "CROSSROADS",
    "XRDS"
  ],
  "CURV": [
    "CURVE",
    "CURV"
  ],
  "DL": [
    "DALE",
    "DL"
  ],
  "DM": [
    "DAM",
    "DM"
  ],
  "DV": [
    "DIVIDE",
    "DIV",
    "DV",
    "DVD"
  ],
  "DR": [
    "DRIVE",
    "DR",
    "DRIV",
    "DRIVE",
    "DRV"
  ],
  "DRS": [
    "DRIVES",
    "DRS"
  ],
  "EST": [
    "ESTATE",
    "EST"
  ],
  "ESTS": [
    "ESTATES",
    "ESTS"
  ],
  "EXPY": [
    "EXPRESSWAY",
    "EXP",
    "EXPY",
    "EXPR",
    "EXPRESS",
    "EXPW"
  ],
  "EXT": [
    "EXTENSION",
    "EXT",
    "EXTN",
    "EXTNSN"
  ],
  "EXTS": [
    "EXTENSIONS",
    "EXTS"
  ],
  "FALL": [
    "FALL"
  ],
  "FLS": [
    "FALLS",
    "FLS"
  ],
  "FRY": [
    "FERRY",
    "FRY",
    "FRRY"
  ],
  "FLD": [
    "FIELD",
    "FLD"
  ],
  "FLDS": [
    "FIELDS",
    "FLDS"
  ],
  "FLT": [
    "FLAT",
    "FLT"
  ],
  "FLTS": [
    "FLATS",
    "FLTS"
  ],
  "FRD": [
    "FORD",
    "FRD"
  ],
  "FRDS": [
    "FORDS",
    "FRDS"
  ],
  "FRST": [
    "FOREST",
    "FRST",
    "FORESTS"
  ],
  "FRG": [
    "FORGE",
    "FORG",
    "FRG"
  ],
  "FRGS": [
    "FORGES",
    "FRGS"
  ],
  "FRK": [
    "FORK",
    "FRK"
  ],
  "FRKS": [
    "FORKS",
    "FRKS"
  ],
  "FT": [
    "FORT",
    "FT",
    "FRT"
  ],
  "FWY": [
    "FREEWAY",
    "FWY",
    "FREEWY",
    "FRWAY",
    "FRWY"
  ],
  "GRDN": [
    "GARDEN",
    "GDN",
    "GARDN",
    "GRDEN"
  ],
  "GDNS": [
    "GARDENS",
    "GDNS",
    "GRDNS"
  ],
  "GTWY": [
    "GATEWAY",
    "GTWY",
    "GATEWY",
    "GATWAY",
    "GTWAY"
  ],
  "GLN": [
    "GLEN",
    "GLN"
  ],
  "GLNS": [
    "GLENS",
    "GLNS"
  ],
  "GRN": [
    "GREEN",
    "GRN"
  ],
  "GRNS": [
    "GREENS",
    "GRNS"
  ],
  "GRV": [
    "GROVE",
    "GROV",
    "GRV"
  ],
  "GRVS": [
    "GROVES",
    "GRVS"
  ],
  "HBR": [
    "HARBOR",
    "HARB",
    "HBR",
    "HARBR",
    "HRBOR"
  ],
  "HBRS": [
    "HARBORS",
    "HBRS"
  ],
  "HVN": [
    "HAVEN",
    "HVN"
  ],
  "HTS": [
    "HEIGHTS",
    "HT",
    "HTS"
  ],
  "HWY": [
    "HIGHWAY",
    "HWY",
    "HIGHWY",
    "HIWAY",
    "HIWY",
    "HWAY"
  ],
  "HL": [
    "HILL",
    "HL"
  ],
  "HLS": [
    "HILLS",
    "HLS"
  ],
  "HOLW": [
    "HOLLOW",
    "HLLW",
    "HOLW",
    "HOLLOWS",
    "HOLWS"
  ],
  "INLT": [
    "INLET",
    "INLT"
  ],
  "IS": [
    "ISLAND",
    "IS",
    "ISLND"
  ],
  "ISS": [
    "ISLANDS",
    "ISS",
    "ISLNDS"
  ],
  "ISLE": [
    "ISLE",
    "ISLES"
  ],
  "JCT": [
    "JUNCTION",
    "JCT",
    "JCTION",
    "JCTN",
    "JUNCTN",
    "JUNCTON"
  ],
  "JCTS": [
    "JUNCTIONS",
    "JCTNS",
    "JCTS"
  ],
  "KY": [
    "KEY",
    "KY"
  ],
  "KYS": [
    "KEYS",
    "KYS"
  ],
  "KNL": [
    "KNOLL",
    "KNL",
    "KNOL"
  ],
  "KNLS": [
    "KNOLLS",
    "KNLS"
  ],
  "LK": [
    "LAKE",
    "LK"
  ],
  "LKS": [
    "LAKES",
    "LKS"
  ],
  "LAND": [
    "LAND"
  ],
  "LNDG": [
    "LANDING",
    "LNDG",
    "LNDNG"
  ],
  "LN": [
    "LANE",
    "LN"
  ],
  "LGT": [
    "LIGHT",
    "LGT"
  ],
  "LGTS": [
    "LIGHTS",
    "LGTS"
  ],
  "LF": [
    "LOAF",
    "LF"
  ],
  "LCK": [
    "LOCK",
    "LCK"
  ],
  "LCKS": [
    "LOCKS",
    "LCKS"
  ],
  "LDG": [
    "LODGE",
    "LDG",
    "LDG",
    "LDGE",
    "LODG"
  ],
  "LOOP": [
    "LOOPS",
    "LOOP"
  ],
  "MALL": [
    "MALL"
  ],
  "MNR": [
    "MANOR",
    "MNR"
  ],
  "MNRS": [
    "MANORS",
    "MNRS"
  ],
  "MDW": [
    "MEADOW"
  ],
  "MDWS": [
    "MEADOWS",
    "MDWS",
    "MEADOWS",
    "MEDOWS"
  ],
  "MEWS": [
    "MEWS"
  ],
  "ML": [
    "MILL",
    "ML"
  ],
  "MLS": [
    "MILLS",
    "MLS"
  ],
  "MSN": [
    "MISSION",
    "MISSN",
    "MSN",
    "MSSN"
  ],
  "MTWY": [
    "MOTORWAY",
    "MTWY"
  ],
  "MT": [
    "MOUNT",
    "MNT",
    "MT"
  ],
  "MTN": [
    "MOUNTAIN",
    "MNTAIN",
    "MTN",
    "MNTN",
    "MOUNTIN",
    "MTIN"
  ],
  "MTNS": [
    "MOUNTAINS",
    "MNTNS"
  ],
  "NCK": [
    "NECK",
    "NCK"
  ],
  "ORCH": [
    "ORCHARD",
    "ORCH",
    "ORCHRD"
  ],
  "OVAL": [
    "OVAL",
    "OVL"
  ],
  "OPAS": [
    "OVERPASS",
    "OPAS"
  ],
  "PARK": [
    "PARK",
    "PARKS",
    "PRK"
  ],
  "PKWY": [
    "PARKWAY",
    "PKWY",
    "PARKWY",
    "PKWAY",
    "PKY",
    "PARKWAYS",
    "PKWYS"
  ],
  "PASS": [
    "PASS"
  ],
  "PSGE": [
    "PASSAGE",
    "PSGE"
  ],
  "PATH": [
    "PATH",
    "PATHS"
  ],
  "PIKE": [
    "PIKE",
    "PIKES"
  ],
  "PNE": [
    "PINE",
    "PNE"
  ],
  "PNES": [
    "PINES",
    "PNES"
  ],
  "PL": [
    "PLACE",
    "PL"
  ],
  "PLN": [
    "PLAIN",
    "PLN"
  ],
  "PLNS": [
    "PLAINS",
    "PLNS"
  ],
  "PLZ": [
    "PLAZA",
    "PLZ",
    "PLZA"
  ],
  "PT": [
    "POINT",
    "PT"
  ],
  "PTS": [
    "POINTS",
    "PTS"
  ],
  "PRT": [
    "PORT",
    "PRT"
  ],
  "PRTS": [
    "PORTS",
    "PRTS"
  ],
  "PR": [
    "PRAIRIE",
    "PR",
    "PRR"
  ],
  "RADL": [
    "RADIAL",
    "RAD",
    "RADL",
    "RADIEL"
  ],
  "RAMP": [
    "RAMP"
  ],
  "RNCH": [
    "RANCH",
    "RNCH",
    "RANCHES",
    "RNCHS"
  ],
  "RPD": [
    "RAPID",
    "RPD"
  ],
  "RPDS": [
    "RAPIDS",
    "RPDS"
  ],
  "RST": [
    "REST",
    "RST"
  ],
  "RDG": [
    "RIDGE",
    "RDG",
    "RDGE"
  ],
  "RDGS": [
    "RIDGES",
    "RDGS"
  ],
  "RIV": [
    "RIVER",
    "RIV",
    "RVR",
    "RIVR"
  ],
  "RD": [
    "ROAD",
    "RD"
  ],
  "RDS": [
    "ROADS",
    "RDS"
  ],
  "RTE": [
    "ROUTE",
    "RTE"
  ],
  "ROW": [
    "ROW"
  ],
  "RUE": [
    "RUE"
  ],
  "RUN": [
    "RUN"
  ],
  "SHL": [
    "SHOAL",
    "SHL"
  ],
  "SHLS": [
    "SHOALS",
    "SHLS"
  ],
  "SHR": [
    "SHORE",
    "SHOAR",
    "SHR"
  ],
  "SHRS": [
    "SHORES",
    "SHOARS",
    "SHRS"
  ],
  "SKWY": [
    "SKYWAY",
    "SKWY"
  ],
  "SPG": [
    "SPRING",
    "SPG",
    "SPNG",
    "SPRING",
    "SPRNG"
  ],
  "SPGS": [
    "SPRINGS",
    "SPGS",
    "SPNGS",
    "SPRINGS",
    "SPRNGS"
  ],
  "SPUR": [
    "SPUR",
    "SPURS"
  ],
  "SQ": [
    "SQUARE",
    "SQ",
    "SQR",
    "SQRE",
    "SQU"
  ],
  "SQS": [
    "SQUARES",
    "SQRS",
    "SQS"
  ],
  "STA": [
    "STATION",
    "STA",
    "STATN",
    "STN"
  ],
  "STRA": [
    "STRAVENUE",
    "STRA",
    "STRAV",
    "STRAVEN",
    "STRAVN",
    "STRVN",
    "STRVNUE"
  ],
  "STRM": [
    "STREAM",
    "STRM",
    "STREME"
  ],
  "ST": [
    "STREET",
    "ST",
    "STRT",
    "STR"
  ],
  "STS": [
    "STREETS",
    "STS"
  ],
  "SMT": [
    "SUMMIT",
    "SMT",
    "SUMIT",
    "SUMITT"
  ],
  "TER": [
    "TERRACE",
    "TER",
    "TERR"
  ],
  "TRWY": [
    "THROUGHWAY",
    "TRWY"
  ],
  "TRCE": [
    "TRACE",
    "TRCE",
    "TRACES"
  ],
  "TRAK": [
    "TRACK",
    "TRACK",
    "TRAK",
    "TRK",
    "TRKS"
  ],
  "TRFY": [
    "TRAFFICWAY",
    "TRFY"
  ],
  "TRL": [
    "TRAIL",
    "TRL",
    "TRAILS",
    "TRLS"
  ],
  "TRLR": [
    "TRAILER",
    "TRLR",
    "TRLRS"
  ],
  "TUNL": [
    "TUNNEL",
    "TUNEL",
    "TUNL",
    "TUNLS",
    "TUNNELS",
    "TUNNL"
  ],
  "TPKE": [
    "TURNPIKE",
    "TRNPK",
    "TPKE",
    "TURNPK"
  ],
  "UPAS": [
    "UNDERPASS",
    "UPAS"
  ],
  "UN": [
    "UNION",
    "UN"
  ],
  "UNS": [
    "UNIONS",
    "UNS"
  ],
  "VLY": [
    "VALLEY",
    "VLY",
    "VALLY",
    "VLLY"
  ],
  "VLYS": [
    "VALLEYS",
    "VLYS"
  ],
  "VIA": [
    "VIADUCT",
    "VDCT",
    "VIA",
    "VIADCT"
  ],
  "VW": [
    "VIEW",
    "VW"
  ],
  "VWS": [
    "VIEWS",
    "VWS"
  ],
  "VLG": [
    "VILLAGE",
    "VILL",
    "VLG",
    "VILLAG",
    "VILLG",
    "VILLIAGE"
  ],
  "VLGS": [
    "VILLAGES",
    "VLGS"
  ],
  "VL": [
    "VILLE",
    "VL"
  ],
  "VIS": [
    "VISTA",
    "VIS",
    "VIST",
    "VST",
    "VSTA"
  ],
  "WALK": [
    "WALK",
    "WALKS"
  ],
  "WALL": [
    "WALL"
  ],
  "WAY": [
    "WAY",
    "WY"
  ],
  "WAYS": [
    "WAYS",
    "WAYS"
  ],
  "WL": [
    "WELL",
    "WL"
  ],
  "WLS": [
    "WELLS",
    "WLS"
  ]
}